{"hash":"8b5c7fabf061a5895dc75c4f17db632ea5e77661","data":{"dpost":{"id":"ce122e691bdca85fb7995afc4921d345","title":"Nike | Hardcourt Bike Football","content":"<p><a href=\"http://vimeo.com/12451656\" target=\"_blank\" rel=\"nofollow noopener noreferrer\">NIKE TRACKBIKE FOOTBALL (NTF2010)</a> from <a href=\"http://vimeo.com/user1066805\" target=\"_blank\" rel=\"nofollow noopener noreferrer\">YUHZIMI</a> on <a href=\"http://vimeo.com\" target=\"_blank\" rel=\"nofollow noopener noreferrer\">Vimeo</a>.</p>\n<p>Ca y est, le Bike Polo c'est fini !</p>\n"}},"context":{}}