{"hash":"8b5c7fabf061a5895dc75c4f17db632ea5e77661","data":{"dpost":{"id":"0b99fd94a0894084a2e5b6bbce9d10c3","title":"Goldsprint | O'kallaghan's","content":"<p><img src=\"images/goldsprint.jpg\" title=\"Goldsprint\"></p>\n<p>Guidoline organise vendredi 04 juin son premier goldsprint, course de vélos sur rouleaux au pub O'kallaghan's à Rouen.</p>\n<p>Venez vous affronter en duel ou battre votre record sur 300 m ! Et peu être repartir avec un des lots offerts par  Bud Skateshop.</p>\n<p><strong>Goldsprint</strong> 04 juin 2010 18h00 à 23h00</p>\n<p><strong>O'kallaghan's</strong> 13 Place du Général de Gaulle, 76000 Rouen‎ Tél : 02 35 71 46 55‎</p>\n<p><a href=\"http://www.facebook.com/event.php?eid=127052857323587&#x26;index=1\" target=\"_blank\" rel=\"nofollow noopener noreferrer\">Evènement Facebook</a></p>\n"}},"context":{}}